{
    "12": {
        "path": "tv_rating/12.png",
        "width": 240,
        "height": 240
    },
    "15": {
        "path": "tv_rating/15.png",
        "width": 240,
        "height": 240
    },
    "18": {
        "path": "tv_rating/18.png",
        "width": 240,
        "height": 240
    },
    "TV-Y": {
        "path": "tv_rating/TV-Y.png",
        "width": 240,
        "height": 240
    },
    "TV-Y7": {
        "path": "tv_rating/TV-Y7.png",
        "width": 240,
        "height": 240
    },
    "TV-G": {
        "path": "tv_rating/TV-G.png",
        "width": 240,
        "height": 240
    },
    "TV-PG": {
        "path": "tv_rating/TV-PG.png",
        "width": 240,
        "height": 240
    },
    "TV-14": {
        "path": "tv_rating/TV-14.png",
        "width": 240,
        "height": 240
    },
    "TV-MA": {
        "path": "tv_rating/TV-MA.png",
        "width": 240,
        "height": 240
    },
    "G": {
        "path": "tv_rating/G.png",
        "width": 240,
        "height": 209
    },
    "PG": {
        "path": "tv_rating/PG.png",
        "width": 240,
        "height": 164
    },
    "PG-13": {
        "path": "tv_rating/PG-13.png",
        "width": 240,
        "height": 93
    },
    "R": {
        "path": "tv_rating/R.png",
        "width": 240,
        "height": 209
    },
    "NC-17": {
        "path": "tv_rating/NC-17.png",
        "width": 240,
        "height": 71
    },
    "U": {
        "path": "tv_rating/U.png",
        "width": 240,
        "height": 214
    },
    "12A": {
        "path": "tv_rating/12A.png",
        "width": 240,
        "height": 240
    },
    "R18": {
        "path": "tv_rating/R18.png",
        "width": 240,
        "height": 240
    },
    "0+": {
        "path": "tv_rating/0_PLUS.png",
        "width": 240,
        "height": 240
    },
    "6+": {
        "path": "tv_rating/6_PLUS.png",
        "width": 240,
        "height": 240
    },
    "12+": {
        "path": "tv_rating/12_PLUS.png",
        "width": 240,
        "height": 240
    },
    "15+": {
        "path": "tv_rating/15_PLUS.png",
        "width": 240,
        "height": 240
    },
    "18+": {
        "path": "tv_rating/18_PLUS.png",
        "width": 240,
        "height": 240
    },
    "NR": {
        "path": "tv_rating/NR.png",
        "width": 240,
        "height": 60
    },
    "NO RATING": {
        "path": "tv_rating/NO_RATING.png",
        "width": 240,
        "height": 60
    },
    "NOT RATED": {
        "path": "tv_rating/NOT_RATED.png",
        "width": 240,
        "height": 60
    },
    "UR": {
        "path": "tv_rating/UR.png",
        "width": 240,
        "height": 69
    }
}